ezqrcli/__init__.py
ezqrcli/__main__.py
ezqrcli/qr_cli.py
ezqrcli/util.py
ezqrcli-1.0.2.dist-info/entry_points.txt
ezqrcli-1.0.2.dist-info/METADATA
ezqrcli-1.0.2.dist-info/WHEEL
ezqrcli-1.0.2.dist-info/RECORD
