Metadata-Version: 2.1
Name: ezqrcli
Version: 1.0.2
Summary: The easy command line QR code generator
Home-page: https://github.com/DJStompZone/ezqrcli.git
Author: DJ Stomp
Author-email: 85457381+DJStompZone@users.noreply.github.com
Requires-Python: >=3.10,<4.0
Classifier: Programming Language :: Python :: 3
Classifier: Programming Language :: Python :: 3.10
Classifier: Programming Language :: Python :: 3.11
Classifier: Programming Language :: Python :: 3.12
Classifier: Programming Language :: Python :: 3.13
Requires-Dist: argparse (>=1.4.0,<2.0.0)
Requires-Dist: qrcode (>=8.0,<9.0)
Project-URL: Repository, https://github.com/DJStompZone/ezqrcli.git
